{
  "$type": "Bespoke.Sph.Domain.TransformDefinition, domain.sph",
  "MapCollection": {
    "$type": "Bespoke.Sph.Domain.ObjectCollection`1[[Bespoke.Sph.Domain.Map, domain.sph]], domain.sph",
    "$values": [
      {
        "$type": "Bespoke.Sph.Domain.FunctoidMap, domain.sph",
        "__uuid": "",
        "Functoid": "4c6baa30-2483-4e2b-e99f-f3073d16870c",
        "Destination": "version",
        "SourceTypeName": "",
        "DestinationTypeName": "",
        "WebId": "e86bf260-736d-4df1-ca27-32c81a995886"
      },
      {
        "$type": "Bespoke.Sph.Domain.FunctoidMap, domain.sph",
        "__uuid": "",
        "Functoid": "cb73d2a4-0bbf-48b4-feb4-332a151c115b",
        "Destination": "event_type_name_display",
        "SourceTypeName": "",
        "DestinationTypeName": "",
        "WebId": "24f2359d-d111-4b3e-ee93-ea5767ba3502"
      },
      {
        "$type": "Bespoke.Sph.Domain.FunctoidMap, domain.sph",
        "__uuid": "",
        "Functoid": "5b130dd6-2141-429b-8872-d6b456c019ca",
        "Destination": "event_channel",
        "SourceTypeName": "",
        "DestinationTypeName": "",
        "WebId": "54ae3a8a-e984-4760-a3d6-0700aa63a564"
      },
      {
        "$type": "Bespoke.Sph.Domain.FunctoidMap, domain.sph",
        "__uuid": "",
        "Functoid": "d5b326aa-0d53-4a41-ac01-2b96f45c9266",
        "Destination": "physical_channel",
        "SourceTypeName": "",
        "DestinationTypeName": "",
        "WebId": "7ff2f481-5b09-4a2b-bb70-0bd7af98537a"
      },
      {
        "$type": "Bespoke.Sph.Domain.DirectMap, domain.sph",
        "Source": "LocationId",
        "TypeName": "",
        "Destination": "office_no",
        "SourceTypeName": "",
        "DestinationTypeName": "",
        "WebId": "9747239b-0335-464a-d569-4fec46799dd1"
      },
      {
        "$type": "Bespoke.Sph.Domain.DirectMap, domain.sph",
        "Source": "BeatNo",
        "TypeName": "",
        "Destination": "beat_no",
        "SourceTypeName": "",
        "DestinationTypeName": "",
        "WebId": "2e67ab73-4b5e-4fcb-fadc-d40947b05b82"
      },
      {
        "$type": "Bespoke.Sph.Domain.DirectMap, domain.sph",
        "Source": "CourierId",
        "TypeName": "",
        "Destination": "courier_id",
        "SourceTypeName": "",
        "DestinationTypeName": "",
        "WebId": "47d90612-be32-4c6c-eecd-ef12224e123d"
      },
      {
        "$type": "Bespoke.Sph.Domain.DirectMap, domain.sph",
        "Source": "ConsignmentNo",
        "TypeName": "",
        "Destination": "consignment_no",
        "SourceTypeName": "",
        "DestinationTypeName": "",
        "WebId": "a6b2335a-bda8-4219-f2f1-e4b84c01fee3"
      },
      {
        "$type": "Bespoke.Sph.Domain.FunctoidMap, domain.sph",
        "__uuid": "",
        "Functoid": "a453ddc7-ab5f-44a0-a7ea-9e0df451d6e2",
        "Destination": "office_name",
        "SourceTypeName": "",
        "DestinationTypeName": "",
        "WebId": "b6aa1342-c16a-475d-b745-00a6be9bd343"
      },
      {
        "$type": "Bespoke.Sph.Domain.FunctoidMap, domain.sph",
        "__uuid": "",
        "Functoid": "ff2abe7f-cb65-42b7-b61f-8e882679bb08",
        "Destination": "office_next_code",
        "SourceTypeName": "",
        "DestinationTypeName": "",
        "WebId": "c48d4e7b-4469-4ac6-d0c0-c2cab9ef4c4a"
      },
      {
        "$type": "Bespoke.Sph.Domain.FunctoidMap, domain.sph",
        "__uuid": "",
        "Functoid": "5b26038b-809d-4b8b-d46c-44477d6d6321",
        "Destination": "courier_name",
        "SourceTypeName": "",
        "DestinationTypeName": "",
        "WebId": "9afd4bd4-e949-4546-cf46-23080cc23623"
      },
      {
        "$type": "Bespoke.Sph.Domain.FunctoidMap, domain.sph",
        "__uuid": "",
        "Functoid": "1872b7a9-af67-4815-8345-17227d36c6ac",
        "Destination": "data_flag",
        "SourceTypeName": "",
        "DestinationTypeName": "",
        "WebId": "8d21a81f-5f67-4bb5-9bfa-2f3f7a06cb66"
      },
      {
        "$type": "Bespoke.Sph.Domain.FunctoidMap, domain.sph",
        "__uuid": "",
        "Functoid": "bd51d30f-a13e-48b1-cfe2-e076579ab121",
        "Destination": "date_field",
        "SourceTypeName": "",
        "DestinationTypeName": "",
        "WebId": "ebf2309b-31ba-4ea0-db52-ef5912a04c3f"
      },
      {
        "$type": "Bespoke.Sph.Domain.FunctoidMap, domain.sph",
        "__uuid": "",
        "Functoid": "9a573c63-bf9e-45c5-e19c-8b60d191edd3",
        "Destination": "batch_name",
        "SourceTypeName": "",
        "DestinationTypeName": "",
        "WebId": "170ee2c4-0ab9-4950-eb28-5bf9989116ef"
      }
    ]
  },
  "FunctoidCollection": {
    "$type": "Bespoke.Sph.Domain.ObjectCollection`1[[Bespoke.Sph.Domain.Functoid, domain.sph]], domain.sph",
    "$values": [
      {
        "$type": "Bespoke.Sph.Domain.ConstantFunctoid, domain.sph",
        "TypeName": "System.Int32, mscorlib",
        "Value": "0",
        "ArgumentCollection": {
          "$type": "Bespoke.Sph.Domain.ObjectCollection`1[[Bespoke.Sph.Domain.FunctoidArg, domain.sph]], domain.sph",
          "$values": []
        },
        "Name": null,
        "OutputTypeName": null,
        "Label": null,
        "Comment": null,
        "X": 490.0,
        "Y": 456.0,
        "WebId": "4c6baa30-2483-4e2b-e99f-f3073d16870c"
      },
      {
        "$type": "Bespoke.Sph.Domain.ConstantFunctoid, domain.sph",
        "TypeName": "System.String, mscorlib",
        "Value": "Masuk Stesen",
        "ArgumentCollection": {
          "$type": "Bespoke.Sph.Domain.ObjectCollection`1[[Bespoke.Sph.Domain.FunctoidArg, domain.sph]], domain.sph",
          "$values": []
        },
        "Name": null,
        "OutputTypeName": null,
        "Label": null,
        "Comment": null,
        "X": 587.0,
        "Y": 47.0,
        "WebId": "cb73d2a4-0bbf-48b4-feb4-332a151c115b"
      },
      {
        "$type": "Bespoke.Sph.Domain.ConstantFunctoid, domain.sph",
        "TypeName": "System.String, mscorlib",
        "Value": "002",
        "ArgumentCollection": {
          "$type": "Bespoke.Sph.Domain.ObjectCollection`1[[Bespoke.Sph.Domain.FunctoidArg, domain.sph]], domain.sph",
          "$values": []
        },
        "Name": null,
        "OutputTypeName": null,
        "Label": null,
        "Comment": null,
        "X": 558.0,
        "Y": 146.0,
        "WebId": "5b130dd6-2141-429b-8872-d6b456c019ca"
      },
      {
        "$type": "Bespoke.Sph.Domain.ConstantFunctoid, domain.sph",
        "TypeName": "System.String, mscorlib",
        "Value": "S",
        "ArgumentCollection": {
          "$type": "Bespoke.Sph.Domain.ObjectCollection`1[[Bespoke.Sph.Domain.FunctoidArg, domain.sph]], domain.sph",
          "$values": []
        },
        "Name": null,
        "OutputTypeName": null,
        "Label": null,
        "Comment": null,
        "X": 514.0,
        "Y": 167.0,
        "WebId": "d5b326aa-0d53-4a41-ac01-2b96f45c9266"
      },
      {
        "$type": "Bespoke.Sph.Domain.ConfigurationSettingFunctoid, database.lookup",
        "Section": "AppSetting",
        "Key": "oal",
        "ArgumentCollection": {
          "$type": "Bespoke.Sph.Domain.ObjectCollection`1[[Bespoke.Sph.Domain.FunctoidArg, domain.sph]], domain.sph",
          "$values": []
        },
        "Name": null,
        "OutputTypeName": null,
        "Label": null,
        "Comment": null,
        "X": 57.0,
        "Y": 252.0,
        "WebId": "e29546bb-3fa4-4995-ccdf-967a75387e94"
      },
      {
        "$type": "Bespoke.Sph.Domain.SqlServerLookup, database.lookup",
        "DefaultValue": "-",
        "SqlText": "SELECT [name] FROM [dbo].[office] WHERE [location_id] = @value1",
        "ArgumentCollection": {
          "$type": "Bespoke.Sph.Domain.ObjectCollection`1[[Bespoke.Sph.Domain.FunctoidArg, domain.sph]], domain.sph",
          "$values": [
            {
              "$type": "Bespoke.Sph.Domain.FunctoidArg, domain.sph",
              "Name": "connection",
              "TypeName": "System.String, mscorlib",
              "Description": null,
              "Label": null,
              "Comment": null,
              "IsOptional": false,
              "Functoid": "e29546bb-3fa4-4995-ccdf-967a75387e94",
              "Constant": null,
              "Default": null,
              "WebId": null
            },
            {
              "$type": "Bespoke.Sph.Domain.FunctoidArg, domain.sph",
              "Name": "value1",
              "TypeName": "System.String, mscorlib",
              "Description": null,
              "Label": null,
              "Comment": null,
              "IsOptional": true,
              "Functoid": "5c093958-246c-435c-d829-a4352e9c7633",
              "Constant": null,
              "Default": null,
              "WebId": null
            },
            {
              "$type": "Bespoke.Sph.Domain.FunctoidArg, domain.sph",
              "Name": "value2",
              "TypeName": "System.String, mscorlib",
              "Description": null,
              "Label": null,
              "Comment": null,
              "IsOptional": true,
              "Functoid": null,
              "Constant": null,
              "Default": null,
              "WebId": null
            },
            {
              "$type": "Bespoke.Sph.Domain.FunctoidArg, domain.sph",
              "Name": "value3",
              "TypeName": "System.String, mscorlib",
              "Description": null,
              "Label": null,
              "Comment": null,
              "IsOptional": true,
              "Functoid": null,
              "Constant": null,
              "Default": null,
              "WebId": null
            },
            {
              "$type": "Bespoke.Sph.Domain.FunctoidArg, domain.sph",
              "Name": "value4",
              "TypeName": "System.String, mscorlib",
              "Description": null,
              "Label": null,
              "Comment": null,
              "IsOptional": true,
              "Functoid": null,
              "Constant": null,
              "Default": null,
              "WebId": null
            }
          ]
        },
        "Name": null,
        "OutputTypeName": "System.String, mscorlib",
        "Label": null,
        "Comment": null,
        "X": 217.0,
        "Y": 215.0,
        "WebId": "a453ddc7-ab5f-44a0-a7ea-9e0df451d6e2"
      },
      {
        "$type": "Bespoke.Sph.Domain.SourceFunctoid, domain.sph",
        "Field": "LocationId",
        "ArgumentCollection": {
          "$type": "Bespoke.Sph.Domain.ObjectCollection`1[[Bespoke.Sph.Domain.FunctoidArg, domain.sph]], domain.sph",
          "$values": []
        },
        "Name": "",
        "OutputTypeName": "",
        "Label": "",
        "Comment": "",
        "X": 0.0,
        "Y": 0.0,
        "WebId": "5c093958-246c-435c-d829-a4352e9c7633"
      },
      {
        "$type": "Bespoke.Sph.Domain.SqlServerLookup, database.lookup",
        "DefaultValue": "-",
        "SqlText": "SELECT [nextcode] FROM [dbo].[office] WHERE [location_id] = @value1",
        "ArgumentCollection": {
          "$type": "Bespoke.Sph.Domain.ObjectCollection`1[[Bespoke.Sph.Domain.FunctoidArg, domain.sph]], domain.sph",
          "$values": [
            {
              "$type": "Bespoke.Sph.Domain.FunctoidArg, domain.sph",
              "Name": "connection",
              "TypeName": "System.String, mscorlib",
              "Description": null,
              "Label": null,
              "Comment": null,
              "IsOptional": false,
              "Functoid": "e29546bb-3fa4-4995-ccdf-967a75387e94",
              "Constant": null,
              "Default": null,
              "WebId": null
            },
            {
              "$type": "Bespoke.Sph.Domain.FunctoidArg, domain.sph",
              "Name": "value1",
              "TypeName": "System.String, mscorlib",
              "Description": null,
              "Label": null,
              "Comment": null,
              "IsOptional": true,
              "Functoid": "6fc04eb7-bf17-46d1-96ad-ccc5d21ecaaf",
              "Constant": null,
              "Default": null,
              "WebId": null
            },
            {
              "$type": "Bespoke.Sph.Domain.FunctoidArg, domain.sph",
              "Name": "value2",
              "TypeName": "System.String, mscorlib",
              "Description": null,
              "Label": null,
              "Comment": null,
              "IsOptional": true,
              "Functoid": null,
              "Constant": null,
              "Default": null,
              "WebId": null
            },
            {
              "$type": "Bespoke.Sph.Domain.FunctoidArg, domain.sph",
              "Name": "value3",
              "TypeName": "System.String, mscorlib",
              "Description": null,
              "Label": null,
              "Comment": null,
              "IsOptional": true,
              "Functoid": null,
              "Constant": null,
              "Default": null,
              "WebId": null
            },
            {
              "$type": "Bespoke.Sph.Domain.FunctoidArg, domain.sph",
              "Name": "value4",
              "TypeName": "System.String, mscorlib",
              "Description": null,
              "Label": null,
              "Comment": null,
              "IsOptional": true,
              "Functoid": null,
              "Constant": null,
              "Default": null,
              "WebId": null
            }
          ]
        },
        "Name": null,
        "OutputTypeName": "System.String, mscorlib",
        "Label": null,
        "Comment": null,
        "X": 234.0,
        "Y": 296.0,
        "WebId": "ff2abe7f-cb65-42b7-b61f-8e882679bb08"
      },
      {
        "$type": "Bespoke.Sph.Domain.SourceFunctoid, domain.sph",
        "Field": "LocationId",
        "ArgumentCollection": {
          "$type": "Bespoke.Sph.Domain.ObjectCollection`1[[Bespoke.Sph.Domain.FunctoidArg, domain.sph]], domain.sph",
          "$values": []
        },
        "Name": "",
        "OutputTypeName": "",
        "Label": "",
        "Comment": "",
        "X": 0.0,
        "Y": 0.0,
        "WebId": "6fc04eb7-bf17-46d1-96ad-ccc5d21ecaaf"
      },
      {
        "$type": "Bespoke.Sph.Domain.SqlServerLookup, database.lookup",
        "DefaultValue": "-",
        "SqlText": "SELECT [name] FROM [dbo].[oal_user] WHERE [user_id] = @value1",
        "ArgumentCollection": {
          "$type": "Bespoke.Sph.Domain.ObjectCollection`1[[Bespoke.Sph.Domain.FunctoidArg, domain.sph]], domain.sph",
          "$values": [
            {
              "$type": "Bespoke.Sph.Domain.FunctoidArg, domain.sph",
              "Name": "connection",
              "TypeName": "System.String, mscorlib",
              "Description": null,
              "Label": null,
              "Comment": null,
              "IsOptional": false,
              "Functoid": "e29546bb-3fa4-4995-ccdf-967a75387e94",
              "Constant": null,
              "Default": null,
              "WebId": null
            },
            {
              "$type": "Bespoke.Sph.Domain.FunctoidArg, domain.sph",
              "Name": "value1",
              "TypeName": "System.String, mscorlib",
              "Description": null,
              "Label": null,
              "Comment": null,
              "IsOptional": true,
              "Functoid": "f0e16b1a-6a8b-4472-ec4d-fdfd4cee75d2",
              "Constant": null,
              "Default": null,
              "WebId": null
            },
            {
              "$type": "Bespoke.Sph.Domain.FunctoidArg, domain.sph",
              "Name": "value2",
              "TypeName": "System.String, mscorlib",
              "Description": null,
              "Label": null,
              "Comment": null,
              "IsOptional": true,
              "Functoid": null,
              "Constant": null,
              "Default": null,
              "WebId": null
            },
            {
              "$type": "Bespoke.Sph.Domain.FunctoidArg, domain.sph",
              "Name": "value3",
              "TypeName": "System.String, mscorlib",
              "Description": null,
              "Label": null,
              "Comment": null,
              "IsOptional": true,
              "Functoid": null,
              "Constant": null,
              "Default": null,
              "WebId": null
            },
            {
              "$type": "Bespoke.Sph.Domain.FunctoidArg, domain.sph",
              "Name": "value4",
              "TypeName": "System.String, mscorlib",
              "Description": null,
              "Label": null,
              "Comment": null,
              "IsOptional": true,
              "Functoid": null,
              "Constant": null,
              "Default": null,
              "WebId": null
            }
          ]
        },
        "Name": null,
        "OutputTypeName": "System.String, mscorlib",
        "Label": null,
        "Comment": null,
        "X": 264.0,
        "Y": 375.0,
        "WebId": "5b26038b-809d-4b8b-d46c-44477d6d6321"
      },
      {
        "$type": "Bespoke.Sph.Domain.SourceFunctoid, domain.sph",
        "Field": "CourierId",
        "ArgumentCollection": {
          "$type": "Bespoke.Sph.Domain.ObjectCollection`1[[Bespoke.Sph.Domain.FunctoidArg, domain.sph]], domain.sph",
          "$values": []
        },
        "Name": "",
        "OutputTypeName": "",
        "Label": "",
        "Comment": "",
        "X": 0.0,
        "Y": 0.0,
        "WebId": "f0e16b1a-6a8b-4472-ec4d-fdfd4cee75d2"
      },
      {
        "$type": "Bespoke.Sph.Domain.ScriptFunctoid, domain.sph",
        "Expression": "var isBaby = item.ConsignmentNo.StartsWith(\"EA\") || item.ConsignmentNo.StartsWith(\"EB\");\r\nreturn isBaby ? \"1\" : \"0\";",
        "ArgumentCollection": {
          "$type": "Bespoke.Sph.Domain.ObjectCollection`1[[Bespoke.Sph.Domain.FunctoidArg, domain.sph]], domain.sph",
          "$values": []
        },
        "Name": "CheckBaby",
        "OutputTypeName": "System.String, mscorlib",
        "Label": null,
        "Comment": null,
        "X": 420.0,
        "Y": 391.0,
        "WebId": "1872b7a9-af67-4815-8345-17227d36c6ac"
      },
      {
        "$type": "Bespoke.Sph.Domain.ScriptFunctoid, domain.sph",
        "Expression": "return new DateTime(item.Date.Year,item.Date.Month, item.Date.Day, item.Time.Hour, item.Time.Minute, item.Time.Second);",
        "ArgumentCollection": {
          "$type": "Bespoke.Sph.Domain.ObjectCollection`1[[Bespoke.Sph.Domain.FunctoidArg, domain.sph]], domain.sph",
          "$values": []
        },
        "Name": "GetDateTime",
        "OutputTypeName": "System.DateTime, mscorlib",
        "Label": null,
        "Comment": null,
        "X": 435.0,
        "Y": 496.0,
        "WebId": "bd51d30f-a13e-48b1-cfe2-e076579ab121"
      },
      {
        "$type": "Bespoke.Sph.Domain.ScriptFunctoid, domain.sph",
        "Expression": "return string.Format(\"sa_sip_{0}_{1}\", item.Date, item.Time);",
        "ArgumentCollection": {
          "$type": "Bespoke.Sph.Domain.ObjectCollection`1[[Bespoke.Sph.Domain.FunctoidArg, domain.sph]], domain.sph",
          "$values": []
        },
        "Name": "GetBatchName",
        "OutputTypeName": "System.String, mscorlib",
        "Label": null,
        "Comment": null,
        "X": 489.0,
        "Y": 371.0,
        "WebId": "9a573c63-bf9e-45c5-e19c-8b60d191edd3"
      }
    ]
  },
  "InputCollection": {
    "$type": "Bespoke.Sph.Domain.ObjectCollection`1[[Bespoke.Sph.Domain.MethodArg, domain.sph]], domain.sph",
    "$values": []
  },
  "ReferencedAssemblyCollection": {
    "$type": "Bespoke.Sph.Domain.ObjectCollection`1[[Bespoke.Sph.Domain.ReferencedAssembly, domain.sph]], domain.sph",
    "$values": []
  },
  "Name": "RtsSipToOalSipEventNew",
  "Description": "",
  "InputTypeName": "Bespoke.PosEntt.Sips.Domain.Sip, PosEntt.Sip",
  "OutputTypeName": "Bespoke.PosEntt.Adapters.Oal.dbo_sip_event_new, PosEntt.Oal",
  "IsPublished": true,
  "CreatedBy": "admin",
  "Id": "rts-sip-to-oal-sip-event-new",
  "CreatedDate": "2016-11-01T10:09:25.6590498+08:00",
  "ChangedBy": "admin",
  "ChangedDate": "2016-11-01T10:40:46.0939622+08:00",
  "WebId": "ce3aa93b-a87b-4c78-93cb-110b49cb2f74"
}