{
  "$type": "Bespoke.Sph.Domain.Trigger, domain.sph",
  "RuleCollection": {
    "$type": "Bespoke.Sph.Domain.ObjectCollection`1[[Bespoke.Sph.Domain.Rule, domain.sph]], domain.sph",
    "$values": []
  },
  "ActionCollection": {
    "$type": "Bespoke.Sph.Domain.ObjectCollection`1[[Bespoke.Sph.Domain.CustomAction, domain.sph]], domain.sph",
    "$values": [
      {
        "$type": "Bespoke.Sph.Messaging.MessagingAction, trigger.action.messaging",
        "OutboundMap": "rts-reve-to-oal-revex-event-new",
        "Adapter": "Oal",
        "Operation": null,
        "Table": "revex_event_new",
        "Schema": null,
        "Crud": "Insert",
        "Retry": 5,
        "RetryInterval": 5000,
        "RetryIntervalTimeSpan": 1,
        "Title": "ToOalReveEventNew",
        "IsActive": true,
        "TriggerId": null,
        "Note": null,
        "WebId": "106d8908-57a5-4b5d-ed97-7d506be01f92"
      }
    ]
  },
  "ReferencedAssemblyCollection": {
    "$type": "Bespoke.Sph.Domain.ObjectCollection`1[[Bespoke.Sph.Domain.ReferencedAssembly, domain.sph]], domain.sph",
    "$values": [
      {
        "$type": "Bespoke.Sph.Domain.ReferencedAssembly, domain.sph",
        "Name": "PosEntt.Oal",
        "FullName": "PosEntt.Oal, Version=0.0.0.0, Culture=neutral, PublicKeyToken=null",
        "Version": "0.0.0.0",
        "Location": "C:\\project\\work\\entt.rts\\output\\PosEntt.Oal.dll",
        "IsGac": false,
        "IsStrongName": false,
        "RuntimeVersion": "v4.0.30319",
        "WebId": null
      },
      {
        "$type": "Bespoke.Sph.Domain.ReferencedAssembly, domain.sph",
        "Name": "PosEntt.RtsReveToOalRevexEventNew",
        "FullName": "PosEntt.RtsReveToOalRevexEventNew, Version=0.0.0.0, Culture=neutral, PublicKeyToken=null",
        "Version": "0.0.0.0",
        "Location": "C:\\project\\work\\entt.rts\\output\\PosEntt.RtsReveToOalRevexEventNew.dll",
        "IsGac": false,
        "IsStrongName": false,
        "RuntimeVersion": "v4.0.30319",
        "WebId": null
      }
    ]
  },
  "RequeueFilterCollection": {
    "$type": "Bespoke.Sph.Domain.ObjectCollection`1[[Bespoke.Sph.Domain.ExceptionFilter, domain.sph]], domain.sph",
    "$values": []
  },
  "Name": "RtsReveToOal",
  "Entity": "Reve",
  "TypeOf": "Bespoke.PosEntt.Reves.Domain.Reve, PosEntt.Reve",
  "Note": "",
  "IsActive": true,
  "IsFiredOnAdded": true,
  "IsFiredOnDeleted": false,
  "IsFiredOnChanged": false,
  "FiredOnOperations": "",
  "ClassName": "ReveRtsReveToOalTriggerSubscriber",
  "CodeNamespace": "Bespoke.PosEntt.TriggerSubscribers",
  "CreatedBy": "admin",
  "Id": "reve-rts-reve-to-oal",
  "CreatedDate": "2016-11-14T13:09:31.3588873+08:00",
  "ChangedBy": "admin",
  "ChangedDate": "2016-11-14T13:10:27.4083767+08:00",
  "WebId": "99313290-55f3-468d-8d29-a245b6338792"
}